rossum_api/__init__.py
rossum_api/dtos.py
rossum_api/exceptions.py
rossum_api/py.typed
rossum_api/types.py
rossum_api/utils.py
rossum_api/clients/__init__.py
rossum_api/clients/external_async_client.py
rossum_api/clients/external_sync_client.py
rossum_api/clients/internal_async_client.py
rossum_api/clients/internal_sync_client.py
rossum_api/clients/types.py
rossum_api/domain_logic/__init__.py
rossum_api/domain_logic/annotations.py
rossum_api/domain_logic/documents.py
rossum_api/domain_logic/emails.py
rossum_api/domain_logic/pagination.py
rossum_api/domain_logic/resources.py
rossum_api/domain_logic/retry.py
rossum_api/domain_logic/search.py
rossum_api/domain_logic/sideloads.py
rossum_api/domain_logic/tasks.py
rossum_api/domain_logic/upload.py
rossum_api/domain_logic/urls.py
rossum_api/models/__init__.py
rossum_api/models/annotation.py
rossum_api/models/automation_blocker.py
rossum_api/models/connector.py
rossum_api/models/document.py
rossum_api/models/document_relation.py
rossum_api/models/email.py
rossum_api/models/email_template.py
rossum_api/models/engine.py
rossum_api/models/group.py
rossum_api/models/hook.py
rossum_api/models/inbox.py
rossum_api/models/organization.py
rossum_api/models/py.typed
rossum_api/models/queue.py
rossum_api/models/relation.py
rossum_api/models/rule.py
rossum_api/models/schema.py
rossum_api/models/task.py
rossum_api/models/upload.py
rossum_api/models/user.py
rossum_api/models/workspace.py
rossum_api-3.7.1.dist-info/licenses/LICENSE
rossum_api-3.7.1.dist-info/METADATA
rossum_api-3.7.1.dist-info/WHEEL
rossum_api-3.7.1.dist-info/top_level.txt
rossum_api-3.7.1.dist-info/RECORD
